LICENSE
README.md
setup.py
xtelnet/__init__.py
xtelnet/__main__.py
xtelnet/multiple_sessions.py
xtelnet/negotiations_flags.py
xtelnet/prompts.py
xtelnet/socket_client.py
xtelnet/telnet_client.py
xtelnet.egg-info/PKG-INFO
xtelnet.egg-info/SOURCES.txt
xtelnet.egg-info/dependency_links.txt
xtelnet.egg-info/entry_points.txt
xtelnet.egg-info/requires.txt
xtelnet.egg-info/top_level.txt