Metadata-Version: 2.1
Name: xtelnet
Version: 2.2.7
Summary: the best alternative to telnetlib as a telnet client
Home-page: https://github.com/AlaBouali/xtelnet
Author: AlaBouali
Author-email: ala.bouali.1997@gmail.com
License: MIT License
Classifier: Programming Language :: Python
Classifier: License :: OSI Approved :: MIT License 
Requires-Python: >=2.7
License-File: LICENSE
Requires-Dist: PySocks
